{
    "module-identifier": "androidx.compose.ui:ui-tooling-data",
    "components": [
        {
            "version": "1.8.1",
            "variants": [
                {
                    "artifacts": {
                        "ui-tooling-data-metadata-1.8.1.jar": "11c2ead8479cca75cd30e01d841c25a9de95f5f5c8867da2743523b91725171b"
                    }
                }
            ],
            "dependency-locking-groups": [
                "build-classpath"
            ]
        }
    ]
}
