{
    "module-identifier": "androidx.annotation:annotation-iosarm64",
    "components": [
        {
            "version": "1.9.1",
            "variants": [
                {
                    "artifacts": {
                        "annotation-iosarm64-1.9.1-metadata.jar": "39a5c38f5e98e41a3c64f1b604ca19756c6ba59dc81b848adbad4ef3db7e8601"
                    }
                },
                {
                    "artifacts": {
                        "annotation.klib": "7f5b56c89b8acbde25178a480de6f6bb8de23f2ac5c5f765471b349567ffa93c"
                    }
                }
            ],
            "dependency-locking-groups": [
                "build-classpath"
            ]
        }
    ]
}
