{
    "module-identifier": "co.touchlab:stately-strict-iossimulatorarm64",
    "components": [
        {
            "version": "2.0.7",
            "variants": [
                {
                    "artifacts": {
                        "stately-strict-iossimulatorarm64-2.0.7-metadata.jar": "e31d1f2b485d66ac4c842c08ed12c7dc396801f264458e68d1d4bb953605771e"
                    }
                },
                {
                    "artifacts": {
                        "stately-strict.klib": "d9449e36c703b7c64b11d9945cdd899d1a5e9c334e5e1a2376f49cbb663cf5ef"
                    }
                }
            ],
            "dependency-locking-groups": [
                "build-classpath"
            ]
        }
    ]
}
