{
    "module-identifier": "co.touchlab:kermit-core-iosarm64",
    "components": [
        {
            "version": "2.0.5",
            "variants": [
                {
                    "artifacts": {
                        "kermit-core-cinterop-os_log.klib": "abe8b0a859b8fbb3b974a44c8e6215bfb0652939b328d9d95749819c552c7d91",
                        "kermit-core.klib": "632f47b3b91a767252f7e011c522c5db4d444d0bb1f8cf06d9004d7c2d0736f5"
                    }
                },
                {
                    "artifacts": {
                        "kermit-core-iosarm64-2.0.5-metadata.jar": "9b59c7acf755feb5f8e007b77bdea038473cfd44954b3ba6569f25cfcae9bda6"
                    }
                }
            ],
            "dependency-locking-groups": [
                "build-classpath"
            ]
        }
    ]
}
