{
    "module-identifier": "com.android.tools:sdklib",
    "components": [
        {
            "version": "31.10.1",
            "variants": [
                {
                    "artifacts": {
                        "sdklib-31.10.1.jar": "af153d7550264b9f79ef4a02b0f8917ed4d5a276644ce8de39d7ecf66794de24"
                    }
                }
            ],
            "dependency-locking-groups": [
                "gradle-plugins[bitkey]"
            ]
        },
        {
            "version": "31.4.2",
            "variants": [
                {
                    "artifacts": {
                        "sdklib-31.4.2.jar": "51b499a01f398d6b671911f9d85b3114fde5e462f57b0040c5f0fcab1bdbfc22"
                    }
                }
            ],
            "dependency-locking-groups": [
                "build-classpath"
            ]
        }
    ]
}
