{
    "module-identifier": "com.squareup.wire:wire-grpc-server-generator",
    "components": [
        {
            "version": "4.9.9",
            "variants": [
                {
                    "artifacts": {
                        "wire-grpc-server-generator-4.9.9.jar": "82c90e48eee436930ba11fd8e4c6a338846feb5d3a39b2b6ca5e877fe036fca7"
                    }
                }
            ],
            "dependency-locking-groups": [
                "gradle-plugins[bitkey]"
            ]
        }
    ]
}
