{
    "module-identifier": "com.squareup.wire:wire-kotlin-generator",
    "components": [
        {
            "version": "5.3.5",
            "variants": [
                {
                    "artifacts": {
                        "wire-kotlin-generator-5.3.5.jar": "1753cfa0e8e4a9c603f592011f5036fbc4655d15d090b92b720e172d136f13bb"
                    }
                }
            ],
            "dependency-locking-groups": [
                "gradle-plugins[bitkey]"
            ]
        }
    ]
}
