{
    "module-identifier": "com.google.protobuf:protobuf-java",
    "components": [
        {
            "version": "3.22.3",
            "variants": [
                {
                    "artifacts": {
                        "protobuf-java-3.22.3.jar": "59d388ea6a2d2d76ae8efff7fd4d0c60c6f0f464c3d3ab9be8e5add092975708"
                    }
                }
            ],
            "dependency-locking-groups": [
                "build-classpath"
            ]
        },
        {
            "version": "3.25.5",
            "variants": [
                {
                    "artifacts": {
                        "protobuf-java-3.25.5.jar": "8540247fad9e06baefa8fb45eb313802d019f485f14300e0f9d6b556ed88e753"
                    }
                }
            ],
            "dependency-locking-groups": [
                "gradle-plugins[bitkey]"
            ]
        }
    ]
}
