{
    "module-identifier": "com.squareup.wire:wire-runtime-iossimulatorarm64",
    "components": [
        {
            "version": "4.9.11",
            "variants": [
                {
                    "artifacts": {
                        "wire-runtime-iossimulatorarm64-4.9.11-metadata.jar": "40bd996c842cbca2cc8c4b427554286b96084154feb37d9cb95e6a6cd9141f93"
                    }
                },
                {
                    "artifacts": {
                        "wire-runtime.klib": "7c92a83b3dbe210a46e10631b1ba60a0c56ac392818ea9611309a28e014cebe1"
                    }
                }
            ],
            "dependency-locking-groups": [
                "build-classpath"
            ]
        }
    ]
}
