{
    "module-identifier": "com.squareup.wire:wire-java-generator",
    "components": [
        {
            "version": "5.3.5",
            "variants": [
                {
                    "artifacts": {
                        "wire-java-generator-5.3.5.jar": "e38d92c3e370cb997f7712dd1a3ae6f9b16bfe05284115ee5b798e1458aa9a51"
                    }
                }
            ],
            "dependency-locking-groups": [
                "gradle-plugins[bitkey]"
            ]
        }
    ]
}
