{
    "module-identifier": "io.kotest:kotest-assertions-core-iosx64",
    "components": [
        {
            "version": "6.0.0.M1",
            "variants": [
                {
                    "artifacts": {
                        "kotest-assertions-core-iosx64-6.0.0.M1-metadata.jar": "c6deada2fac53b8ea6523dbda77597b128006674616f140f04df23264c6d1aa3"
                    }
                },
                {
                    "artifacts": {
                        "kotest-assertions-core.klib": "05791cb396f177a1a18243d69798e83135f5db96554c9c3e52c73ae1e9f3db95"
                    }
                }
            ],
            "dependency-locking-groups": [
                "build-classpath"
            ]
        }
    ]
}
