{
    "module-identifier": "io.ktor:ktor-serialization-kotlinx-json-jvm",
    "components": [
        {
            "version": "2.3.9",
            "variants": [
                {
                    "artifacts": {
                        "ktor-serialization-kotlinx-json-jvm-2.3.9.jar": "f278c240bbf31d577cf6d961e29c28ac95e0b7c11a76bf07852e86d9a04657d4"
                    }
                }
            ],
            "dependency-locking-groups": [
                "build-classpath"
            ]
        }
    ]
}
