{
    "module-identifier": "io.ktor:ktor-client-mock-iosarm64",
    "components": [
        {
            "version": "2.3.12",
            "variants": [
                {
                    "artifacts": {
                        "ktor-client-mock-iosarm64-2.3.12-metadata.jar": "dd004523cc0464d0bdc7f0549c06d387dcb08f9f94f3ecf3559a6c7c4a3add63"
                    }
                },
                {
                    "artifacts": {
                        "ktor-client-mock.klib": "7b9bf974355385032974fb0f38c539eba64025fa18e73a570005b124a820d937"
                    }
                }
            ],
            "dependency-locking-groups": [
                "build-classpath"
            ]
        }
    ]
}
