{
    "module-identifier": "io.kotest:kotest-assertions-api-iosarm64",
    "components": [
        {
            "version": "5.9.0",
            "variants": [
                {
                    "artifacts": {
                        "kotest-assertions-api-iosarm64-5.9.0-metadata.jar": "b14fd159b653e14d55322f3a2a36bec33a4af043b3b0ff96c77fb79630d4ab6c"
                    }
                },
                {
                    "artifacts": {
                        "kotest-assertions-api.klib": "39b0a0e699a621a1e9950e852cadeaa0f4e1ebeb651c4450c0d7c6ae1b035fd7"
                    }
                }
            ],
            "dependency-locking-groups": [
                "build-classpath"
            ]
        }
    ]
}
