{
    "module-identifier": "org.jetbrains.compose:compose-gradle-plugin",
    "components": [
        {
            "version": "1.7.0",
            "variants": [
                {
                    "artifacts": {
                        "compose-gradle-plugin-1.7.0.jar": "17b721e16f1b5c101a76e16f6f3d2bc3fffeae2b79cc3ef9f41856ed8ec1f392"
                    }
                }
            ],
            "dependency-locking-groups": [
                "gradle-plugins[bitkey]"
            ]
        }
    ]
}
