{
    "module-identifier": "org.jetbrains.compose.foundation:foundation-layout-desktop",
    "components": [
        {
            "version": "1.7.0",
            "variants": [
                {
                    "artifacts": {
                        "foundation-layout-desktop-1.7.0.jar": "d2c867c13ff6632f9880e67dabab2e930007b008b9b22950fc2cc075008eceb6"
                    }
                }
            ],
            "dependency-locking-groups": [
                "build-classpath"
            ]
        }
    ]
}
