{
    "module-identifier": "org.jetbrains.kotlin:kotlin-daemon-embeddable",
    "components": [
        {
            "version": "2.0.21",
            "variants": [
                {
                    "artifacts": {
                        "kotlin-daemon-embeddable-2.0.21.jar": "b1a0a73c5022f8dd05a638c6b76b2bd7361818a1f3860ff2644133b1dd2bdb03"
                    }
                }
            ],
            "dependency-locking-groups": [
                "gradle-plugins[bitkey]",
                "kotlin-compiler"
            ]
        }
    ]
}
