{
    "module-identifier": "org.jetbrains.kotlinx:kotlinx-serialization-core",
    "components": [
        {
            "version": "1.6.3",
            "variants": [
                {
                    "artifacts": {
                        "kotlinx-serialization-core-metadata-1.6.3.jar": "2fa05aff0f33a70da873c09a0ff66b5d54ccdc15e39e7ca4b82633e70c792f34"
                    }
                }
            ],
            "dependency-locking-groups": [
                "build-classpath"
            ]
        }
    ]
}
