{
    "module-identifier": "org.jetbrains.kotlin:kotlin-scripting-common",
    "components": [
        {
            "version": "2.1.20",
            "variants": [
                {
                    "artifacts": {
                        "kotlin-scripting-common-2.1.20.jar": "5fdbf6ae72237ce335d603eb12c49b09bc9c1a33c0c01f1d62e77ff33663cefb"
                    }
                }
            ],
            "dependency-locking-groups": [
                "build-classpath",
                "kotlin-compiler"
            ]
        }
    ]
}
