{
    "module-identifier": "org.jetbrains.compose.material:material-ripple-uikitsimarm64",
    "components": [
        {
            "version": "1.7.0",
            "variants": [
                {
                    "artifacts": {
                        "material-ripple-uikitsimarm64-1.7.0-metadata.jar": "c6deada2fac53b8ea6523dbda77597b128006674616f140f04df23264c6d1aa3"
                    }
                },
                {
                    "artifacts": {
                        "material-ripple.klib": "9ac8c0977aa7e0ec7b6c29b2181a81d1945b8f92395c74a86a206deb0c6b8160"
                    }
                }
            ],
            "dependency-locking-groups": [
                "build-classpath"
            ]
        }
    ]
}
