{
    "module-identifier": "org.jetbrains.compose.components:components-resources-android",
    "components": [
        {
            "version": "1.8.0",
            "variants": [
                {
                    "artifacts": {
                        "library-release.aar": "09b37488fba12649563933ae46aecf23c8896bf781e5959f74b081ce1983d733"
                    }
                }
            ],
            "dependency-locking-groups": [
                "build-classpath"
            ]
        }
    ]
}
